README.md
setup.py
SPRNVA/__init__.py
SPRNVA/animation.py
SPRNVA/audio.py
SPRNVA/color_classification.py
SPRNVA/curves.py
SPRNVA/encryption.py
SPRNVA/entity_controller.py
SPRNVA/grid.py
SPRNVA/image.py
SPRNVA/logic.py
SPRNVA/networking.py
SPRNVA/pathfinding.py
SPRNVA/pcg.py
SPRNVA/primitives_3d.py
SPRNVA/shapes.py
SPRNVA/spritesheetstuff.py
SPRNVA/tilemap.py
SPRNVA/tiles.py
SPRNVA/ui.py
SPRNVA/vector.py
SPRNVA/verlet.py
SPRNVA.egg-info/PKG-INFO
SPRNVA.egg-info/SOURCES.txt
SPRNVA.egg-info/dependency_links.txt
SPRNVA.egg-info/top_level.txt