Metadata-Version: 2.1
Name: SPRNVA
Version: 0.1.0
Summary: A simple gameframework wrapped around the popolar game-making module pygame.
Author: Fabien Schneider
